dailytask/__init__.py
dailytask/dailytask.py
dailytask-0.0.8.dist-info/METADATA
dailytask-0.0.8.dist-info/WHEEL
dailytask-0.0.8.dist-info/top_level.txt
dailytask-0.0.8.dist-info/RECORD
