Metadata-Version: 2.1
Name: dailytask
Version: 0.0.8
Summary: dailytask
Home-page: https://github.com/kkristof200/py_daily_task
Author: Kristof
License: UNKNOWN
Platform: UNKNOWN
Classifier: Programming Language :: Python :: 3
Classifier: License :: OSI Approved :: MIT License
Classifier: Operating System :: OS Independent
Requires-Python: >=3.5
Requires-Dist: colored-logs (>=0.2.10)
Requires-Dist: kcu (>=0.0.65)
Requires-Dist: noraise (>=0.0.9)
Requires-Dist: stopit (>=1.1.2)
